convert_zero_one_based-0.0.1.post0.dist-info/DESCRIPTION.rst
convert_zero_one_based-0.0.1.post0.dist-info/METADATA
convert_zero_one_based-0.0.1.post0.dist-info/RECORD
convert_zero_one_based-0.0.1.post0.dist-info/WHEEL
convert_zero_one_based-0.0.1.post0.dist-info/metadata.json
convert_zero_one_based-0.0.1.post0.dist-info/top_level.txt
zero_one_based_conversion/__init__.py
zero_one_based_conversion/cli.py
zero_one_based_conversion/convert.py
zero_one_based_conversion/coordinate.py
zero_one_based_conversion/tests/__init__.py
zero_one_based_conversion/tests/test_convert.py
zero_one_based_conversion/tests/test_coordinate.py
