Metadata-Version: 2.0
Name: convert-zero-one-based
Version: 0.0.1.post0
Summary: Convert between zero and one based coordinate systems and vice versa
Home-page: https://github.com/bainscou/convert_zero_one_based
Author: Ben Ainscough
Author-email: b.ainscough@wustl.edu
License: MIT
Platform: UNKNOWN
Classifier: Development Status :: 1 - Planning
Classifier: Intended Audience :: Developers
Classifier: Topic :: Utilities
Classifier: License :: OSI Approved :: MIT License
Classifier: Programming Language :: Python :: 3.6
